importfix/__init__.py
importfix/importfix.py
importfix-1.1.dist-info/LICENSE
importfix-1.1.dist-info/METADATA
importfix-1.1.dist-info/WHEEL
importfix-1.1.dist-info/top_level.txt
importfix-1.1.dist-info/RECORD
